Metadata-Version: 2.0
Name: GRR-M2Crypto
Version: 0.22.6.post2
Summary: M2Crypto: A Python crypto and SSL toolkit
Home-page: https://github.com/martinpaljak/M2Crypto
Author: Martin Paljak
Author-email: martin@martinpaljak.net
License: MIT
Platform: any
Classifier: Development Status :: 5 - Production/Stable
Classifier: Intended Audience :: Developers
Classifier: License :: OSI Approved :: MIT License
Classifier: Operating System :: OS Independent
Classifier: Programming Language :: C
Classifier: Programming Language :: Python
Classifier: Topic :: Security :: Cryptography
Classifier: Topic :: Software Development :: Libraries :: Python Modules
Classifier: Programming Language :: Python :: 2.5
Classifier: Programming Language :: Python :: 2.6
Classifier: Programming Language :: Python :: 2.7
Classifier: Programming Language :: Python :: Implementation :: CPython
